micro_swe_agent-1.0.2.dist-info/licenses/LICENSE.md
microsweagent/__init__.py
microsweagent/__main__.py
microsweagent/py.typed
microsweagent/agents/__init__.py
microsweagent/agents/default.py
microsweagent/agents/interactive.py
microsweagent/agents/interactive_textual.py
microsweagent/config/README.md
microsweagent/config/__init__.py
microsweagent/config/default.yaml
microsweagent/config/github_issue.yaml
microsweagent/config/local.yaml
microsweagent/config/local2.tcss
microsweagent/config/extra/__init__.py
microsweagent/config/extra/swebench.yaml
microsweagent/environments/__init__.py
microsweagent/environments/docker.py
microsweagent/environments/local.py
microsweagent/environments/singularity.py
microsweagent/environments/extra/__init__.py
microsweagent/environments/extra/swerex_docker.py
microsweagent/models/__init__.py
microsweagent/models/anthropic.py
microsweagent/models/litellm_model.py
microsweagent/models/test_models.py
microsweagent/models/utils/cache_control.py
microsweagent/models/utils/key_per_thread.py
microsweagent/run/__init__.py
microsweagent/run/github_issue.py
microsweagent/run/hello_world.py
microsweagent/run/inspector.py
microsweagent/run/micro.py
microsweagent/run/micro_extra.py
microsweagent/run/extra/__init__.py
microsweagent/run/extra/config.py
microsweagent/run/extra/swebench.py
microsweagent/run/extra/swebench_single.py
microsweagent/run/extra/utils/batch_progress.py
microsweagent/run/utils/__init__.py
microsweagent/run/utils/save.py
micro_swe_agent-1.0.2.dist-info/METADATA
micro_swe_agent-1.0.2.dist-info/WHEEL
micro_swe_agent-1.0.2.dist-info/entry_points.txt
micro_swe_agent-1.0.2.dist-info/top_level.txt
micro_swe_agent-1.0.2.dist-info/RECORD
