Metadata-Version: 2.4
Name: micro-swe-agent
Version: 1.0.2
Summary: Nano SWE Agent - A simple AI software engineering agent
Author-email: Kilian Lieret <kilian.lieret@posteo.de>, "Carlos E. Jimenez" <carlosej@princeton.edu>
License: MIT License
Project-URL: Documentation, https://micro-swe-agent.com/latest/
Project-URL: Repository, https://github.com/SWE-agent/micro-SWE-agent
Project-URL: Bug Tracker, https://github.com/SWE-agent/micro-SWE-agent/issues
Keywords: nlp,agents,code
Classifier: Development Status :: 3 - Alpha
Classifier: Operating System :: OS Independent
Classifier: Intended Audience :: Developers
Classifier: License :: OSI Approved :: MIT License
Classifier: Programming Language :: Python :: 3.11
Classifier: Programming Language :: Python :: 3 :: Only
Requires-Python: >=3.11
License-File: LICENSE.md
Requires-Dist: pyyaml
Requires-Dist: requests
Requires-Dist: jinja2
Requires-Dist: litellm
Requires-Dist: tenacity
Requires-Dist: rich
Requires-Dist: python-dotenv
Requires-Dist: typer
Requires-Dist: platformdirs
Requires-Dist: textual
Requires-Dist: prompt_toolkit
Provides-Extra: full
Requires-Dist: micro-swe-agent[dev]; extra == "full"
Requires-Dist: swe-rex; extra == "full"
Provides-Extra: dev
Requires-Dist: datasets; extra == "dev"
Requires-Dist: pytest; extra == "dev"
Requires-Dist: pytest-cov; extra == "dev"
Requires-Dist: pytest-asyncio; extra == "dev"
Requires-Dist: pytest-xdist; extra == "dev"
Requires-Dist: pre-commit; extra == "dev"
Requires-Dist: ruff; extra == "dev"
Requires-Dist: mkdocs-include-markdown-plugin; extra == "dev"
Requires-Dist: mkdocstrings[python]>=0.18; extra == "dev"
Requires-Dist: mike; extra == "dev"
Requires-Dist: mkdocs-material; extra == "dev"
Requires-Dist: mkdocs-glightbox; extra == "dev"
Dynamic: license-file
